mcpl/__init__.py
mcpl/__main__.py
mcpl/mcpl.py
mcpl_python-2.2.6.dist-info/licenses/LICENSE
mcpl_python-2.2.6.dist-info/METADATA
mcpl_python-2.2.6.dist-info/WHEEL
mcpl_python-2.2.6.dist-info/entry_points.txt
mcpl_python-2.2.6.dist-info/top_level.txt
mcpl_python-2.2.6.dist-info/RECORD
