Metadata-Version: 2.4
Name: mcpl-python
Version: 2.2.6
Summary: Utilities and API for accessing MCPL (.mcpl) files
Author: MCPL developers (Thomas Kittelmann, et. al.)
License: Apache-2.0
Project-URL: Homepage, https://mctools.github.io/mcpl/
Project-URL: Bug Tracker, https://github.com/mctools/mcpl/issues
Classifier: Programming Language :: Python :: 3
Classifier: License :: OSI Approved :: Apache Software License
Requires-Python: >=3.8
License-File: LICENSE
Requires-Dist: numpy>=1.22
Dynamic: license-file
